pysomq/__init__.py
pysomq/__main__.py
pysomq/_utility.py
pysomq/serial_client.py
pysomq/serial_server.py
pysomq-0.13.dist-info/LICENSE
pysomq-0.13.dist-info/METADATA
pysomq-0.13.dist-info/WHEEL
pysomq-0.13.dist-info/top_level.txt
pysomq-0.13.dist-info/RECORD
