Metadata-Version: 2.1
Name: pysomq
Version: 0.13
Summary: Provide a bidirectional connection to a serial interface via zeroMQ
Home-page: https://github.com/casabre/pySoMQ
Author: Carsten Sauerbrey
Author-email: carsten.sauerbrey@gmail.com
Maintainer: Carsten Sauerbrey
Maintainer-email: carsten.sauerbrey@gmail.com
License: MIT
Keywords: utility,serial,zeroMQ
Platform: Unix
Platform: Linux
Platform: Windows
Classifier: Development Status :: 4 - Beta
Classifier: Programming Language :: Python :: 3
Classifier: License :: OSI Approved :: MIT License
Classifier: Operating System :: OS Independent
Requires-Python: >=3.6
License-File: LICENSE
Requires-Dist: pyzmq (>=18.1.0)
Requires-Dist: pyserial (>=3.4)
Requires-Dist: importlib-metadata ; python_version < "3.8"
Provides-Extra: docs
Requires-Dist: sphinx ; extra == 'docs'
Requires-Dist: sphinx-rtd-theme ; extra == 'docs'
Requires-Dist: myst-parser ; extra == 'docs'
Provides-Extra: test
Requires-Dist: pytest ; extra == 'test'
Requires-Dist: coverage[toml] ; extra == 'test'
Requires-Dist: pytest-cov ; extra == 'test'
